<Legislation xmlns="http://www.legislation.gov.uk/namespaces/legislation" xmlns:xsi="http://www.w3.org/2001/XMLSchema-instance" DocumentURI="http://www.legislation.gov.uk/uksi/2012/2885" IdURI="http://www.legislation.gov.uk/id/uksi/2012/2885" NumberOfProvisions="189" xsi:schemaLocation="http://www.legislation.gov.uk/namespaces/legislation http://www.legislation.gov.uk/schema/legislation.xsd" SchemaVersion="1.0" RestrictExtent="E+W" RestrictStartDate="2026-02-13"><ukm:Metadata xmlns:dc="http://purl.org/dc/elements/1.1/" xmlns:dct="http://purl.org/dc/terms/" xmlns:atom="http://www.w3.org/2005/Atom" xmlns:ukm="http://www.legislation.gov.uk/namespaces/metadata">
					<dc:identifier>http://www.legislation.gov.uk/uksi/2012/2885/schedule/1/paragraph/3</dc:identifier><dc:title>The Council Tax Reduction Schemes (Prescribed Requirements) (England) Regulations 2012</dc:title><dc:subject>Council tax</dc:subject><dc:subject>Employment regulations</dc:subject><dc:subject>Tax</dc:subject><dc:subject>Pensions</dc:subject><dc:subject>Benefits</dc:subject><dc:language>en</dc:language><dc:subject scheme="SIheading">COUNCIL TAX, ENGLAND</dc:subject><dc:publisher>Statute Law Database</dc:publisher><dc:modified>2026-02-24</dc:modified><dc:contributor>Expert Participation</dc:contributor><dct:valid>2026-02-13</dct:valid>
					<dc:description>Section 13A of the Local Government Finance Act 1992 (c. 14) (“1992 Act”), substituted by section 10 of the Local Government Finance Act 2012 (c. 17), requires each billing authority in England to make a scheme specifying the reductions which are to apply to amounts of council tax payable by persons, or classes or persons, whom the authority considers are in financial need. Paragraph 2 of Schedule 1A to the 1992 Act sets out matters that must be included in a scheme and gives the Secretary of State power to prescribe by regulations additional requirements, including classes of persons, which must or must not be included in a scheme.</dc:description>
					<atom:link rel="self" href="http://www.legislation.gov.uk/uksi/2012/2885/schedule/1/paragraph/3/data.xml" type="application/xml"/><atom:link rel="http://www.legislation.gov.uk/def/navigation/resources" href="http://www.legislation.gov.uk/uksi/2012/2885/resources" title="More Resources"/>
					<atom:link rel="http://www.legislation.gov.uk/def/navigation/impacts" href="http://www.legislation.gov.uk/uksi/2012/2885/impacts" title="Impact Assessments"/>
					<atom:link rel="http://www.legislation.gov.uk/def/navigation/memorandum" href="http://www.legislation.gov.uk/uksi/2012/2885/memorandum" title="Explanatory Memorandum"/><atom:link rel="http://www.legislation.gov.uk/def/navigation/memorandum/toc" href="http://www.legislation.gov.uk/uksi/2012/2885/memorandum/contents" title="Explanatory Memorandum Table of Contents"/>

					<atom:link rel="http://www.legislation.gov.uk/def/navigation/act" href="http://www.legislation.gov.uk/uksi/2012/2885" title="whole act"/><atom:link rel="http://www.legislation.gov.uk/def/navigation/introduction" href="http://www.legislation.gov.uk/uksi/2012/2885/introduction" title="introduction"/><atom:link rel="http://www.legislation.gov.uk/def/navigation/signature" href="http://www.legislation.gov.uk/uksi/2012/2885/signature" title="signature"/><atom:link rel="http://www.legislation.gov.uk/def/navigation/note" href="http://www.legislation.gov.uk/uksi/2012/2885/note" title="note"/>
					<atom:link rel="http://www.legislation.gov.uk/def/navigation/body" href="http://www.legislation.gov.uk/uksi/2012/2885/body" title="body"/>
					<atom:link rel="http://www.legislation.gov.uk/def/navigation/schedules" href="http://www.legislation.gov.uk/uksi/2012/2885/schedules" title="schedules"/>





					<atom:link rel="alternate" type="application/rdf+xml" href="http://www.legislation.gov.uk/uksi/2012/2885/schedule/1/paragraph/3/data.rdf" title="RDF/XML"/><atom:link rel="alternate" type="application/akn+xml" href="http://www.legislation.gov.uk/uksi/2012/2885/schedule/1/paragraph/3/data.akn" title="AKN"/><atom:link rel="alternate" type="application/xhtml+xml" href="http://www.legislation.gov.uk/uksi/2012/2885/schedule/1/paragraph/3/data.xht" title="HTML snippet"/><atom:link rel="alternate" type="text/html" href="http://www.legislation.gov.uk/uksi/2012/2885/schedule/1/paragraph/3/data.htm" title="Website (XHTML) Default View"/><atom:link rel="alternate" type="text/csv" href="http://www.legislation.gov.uk/uksi/2012/2885/schedule/1/paragraph/3/data.csv" title="CSV"/><atom:link rel="alternate" type="application/pdf" href="http://www.legislation.gov.uk/uksi/2012/2885/schedule/1/paragraph/3/data.pdf" title="PDF"/>
					<atom:link rel="alternate" type="application/akn+xhtml" href="http://www.legislation.gov.uk/uksi/2012/2885/schedule/1/paragraph/3/data.html" title="HTML5 snippet"/>


					<atom:link rel="http://purl.org/dc/terms/tableOfContents" hreflang="en" href="http://www.legislation.gov.uk/uksi/2012/2885/contents" title="Table of Contents"/>

					<atom:link rel="http://purl.org/dc/terms/hasVersion" href="http://www.legislation.gov.uk/uksi/2012/2885/schedule/1/paragraph/3/made" title="made"/><atom:link rel="http://purl.org/dc/terms/hasVersion" href="http://www.legislation.gov.uk/uksi/2012/2885/schedule/1/paragraph/3/2012-11-27" title="2012-11-27"/>

					<atom:link rel="up" href="http://www.legislation.gov.uk/uksi/2012/2885/schedule/1" title="Schedule 1"/><atom:link rel="prev" href="http://www.legislation.gov.uk/uksi/2012/2885/schedule/1/paragraph/2" title="Paragraph; Schedule 1 Paragraph 2"/><atom:link rel="prevInForce" href="http://www.legislation.gov.uk/uksi/2012/2885/schedule/1/paragraph/2" title="Paragraph; Schedule 1 Paragraph 2"/><atom:link rel="next" href="http://www.legislation.gov.uk/uksi/2012/2885/schedule/1/paragraph/4" title="Paragraph; Schedule 1 Paragraph 4"/><atom:link rel="nextInForce" href="http://www.legislation.gov.uk/uksi/2012/2885/schedule/1/paragraph/4" title="Paragraph; Schedule 1 Paragraph 4"/>
					<ukm:SecondaryMetadata><ukm:DocumentClassification><ukm:DocumentCategory Value="secondary"/><ukm:DocumentMainType Value="UnitedKingdomStatutoryInstrument"/><ukm:DocumentStatus Value="revised"/><ukm:DocumentMinorType Value="regulation"/></ukm:DocumentClassification><ukm:Year Value="2012"/><ukm:Number Value="2885"/><ukm:Made Date="2012-11-16"/><ukm:Laid Date="2012-11-22" Class="UnitedKingdomParliament"/><ukm:ComingIntoForce>
<ukm:DateTime Date="2012-11-27"/></ukm:ComingIntoForce><ukm:ISBN Value="9780111530962"/></ukm:SecondaryMetadata>



									<ukm:Notes><ukm:Note IdURI="http://www.legislation.gov.uk/id/uksi/2012/2885/notes"/><ukm:Alternatives><ukm:Alternative URI="http://www.legislation.gov.uk/uksi/2012/2885/pdfs/uksiem_20122885_en.pdf" Date="2012-11-26" Title="Explanatory Memorandum" Size="35051"/></ukm:Alternatives>
								</ukm:Notes>
					<ukm:Alternatives><ukm:Alternative URI="http://www.legislation.gov.uk/uksi/2012/2885/pdfs/uksi_20122885_en.pdf" Date="2012-11-26" Size="440097"/></ukm:Alternatives>
					<ukm:ImpactAssessments>

									<ukm:ImpactAssessment URI="http://www.legislation.gov.uk/ukia/2012/413/pdfs/ukia_20120413_en.pdf" Date="2012-11-26" Title="Council Tax Reduction Schemes (Prescribed Requirements) (England) Regulations" Stage="Consultation" Department="Department for Communities and Local Government" Year="2012" Number="413"/>
								</ukm:ImpactAssessments>
					<ukm:Statistics>
									<ukm:TotalParagraphs Value="190"/>
									<ukm:BodyParagraphs Value="17"/>
									<ukm:ScheduleParagraphs Value="173"/>
									<ukm:AttachmentParagraphs Value="0"/>
									<ukm:TotalImages Value="0"/>
								</ukm:Statistics>
				</ukm:Metadata><Secondary><Schedules RestrictExtent="E+W" RestrictStartDate="2026-02-13"><Schedule DocumentURI="http://www.legislation.gov.uk/uksi/2012/2885/schedule/1" IdURI="http://www.legislation.gov.uk/id/uksi/2012/2885/schedule/1" NumberOfProvisions="47" id="schedule-1" RestrictExtent="E+W" RestrictStartDate="2026-02-13"><Number>SCHEDULE 1</Number><TitleBlock><Title>Pensioners: matters that must be included in an authority’s scheme</Title></TitleBlock><ScheduleBody><Part DocumentURI="http://www.legislation.gov.uk/uksi/2012/2885/schedule/1/part/1" IdURI="http://www.legislation.gov.uk/id/uksi/2012/2885/schedule/1/part/1" NumberOfProvisions="5" id="schedule-1-part-1" RestrictExtent="E+W" RestrictStartDate="2026-02-13"><Number>PART 1</Number><P1group RestrictExtent="E+W" RestrictStartDate="2012-11-27"><Title>Class B: pensioners whose income is greater than the applicable amount</Title><P1 DocumentURI="http://www.legislation.gov.uk/uksi/2012/2885/schedule/1/paragraph/3" IdURI="http://www.legislation.gov.uk/id/uksi/2012/2885/schedule/1/paragraph/3" id="schedule-1-paragraph-3"><Pnumber><CommentaryRef Ref="key-04d1d4b3e916cdc89219e22cdfbe601a"/>3</Pnumber><P1para><Text>On any day class B consists of any person who is a pensioner—</Text><P3 DocumentURI="http://www.legislation.gov.uk/uksi/2012/2885/schedule/1/paragraph/3/a" IdURI="http://www.legislation.gov.uk/id/uksi/2012/2885/schedule/1/paragraph/3/a" id="schedule-1-paragraph-3-a"><Pnumber>a</Pnumber><P3para><Text>who is for that day liable to pay council tax in respect of a dwelling of which he is a resident;</Text></P3para></P3><P3 DocumentURI="http://www.legislation.gov.uk/uksi/2012/2885/schedule/1/paragraph/3/b" IdURI="http://www.legislation.gov.uk/id/uksi/2012/2885/schedule/1/paragraph/3/b" id="schedule-1-paragraph-3-b"><Pnumber>b</Pnumber><P3para><Text>who, subject to paragraph 5, is not absent from the dwelling throughout the day;</Text></P3para></P3><P3 DocumentURI="http://www.legislation.gov.uk/uksi/2012/2885/schedule/1/paragraph/3/c" IdURI="http://www.legislation.gov.uk/id/uksi/2012/2885/schedule/1/paragraph/3/c" id="schedule-1-paragraph-3-c"><Pnumber>c</Pnumber><P3para><Text>in respect of whom a maximum council tax reduction amount can be calculated;</Text></P3para></P3><P3 DocumentURI="http://www.legislation.gov.uk/uksi/2012/2885/schedule/1/paragraph/3/d" IdURI="http://www.legislation.gov.uk/id/uksi/2012/2885/schedule/1/paragraph/3/d" id="schedule-1-paragraph-3-d"><Pnumber>d</Pnumber><P3para><Text>who does not fall within a class of person prescribed for the purposes of paragraph 2(9) of Schedule 1A to the <Abbreviation Expansion="Local Government Finance Act 1992 c. 14">1992 Act</Abbreviation> as a class of person which must not be included in an authority’s scheme;</Text></P3para></P3><P3 DocumentURI="http://www.legislation.gov.uk/uksi/2012/2885/schedule/1/paragraph/3/e" IdURI="http://www.legislation.gov.uk/id/uksi/2012/2885/schedule/1/paragraph/3/e" id="schedule-1-paragraph-3-e"><Pnumber>e</Pnumber><P3para><Text>whose income for the relevant week is greater than his applicable amount;</Text></P3para></P3><P3 DocumentURI="http://www.legislation.gov.uk/uksi/2012/2885/schedule/1/paragraph/3/f" IdURI="http://www.legislation.gov.uk/id/uksi/2012/2885/schedule/1/paragraph/3/f" id="schedule-1-paragraph-3-f"><Pnumber>f</Pnumber><P3para><Text>in respect of whom amount A exceeds amount B where—</Text><P4 DocumentURI="http://www.legislation.gov.uk/uksi/2012/2885/schedule/1/paragraph/3/f/i" IdURI="http://www.legislation.gov.uk/id/uksi/2012/2885/schedule/1/paragraph/3/f/i" id="schedule-1-paragraph-3-f-i"><Pnumber>i</Pnumber><P4para><Text>amount A is the maximum council tax reduction in respect of the day in the applicant’s case; and</Text></P4para></P4><P4 DocumentURI="http://www.legislation.gov.uk/uksi/2012/2885/schedule/1/paragraph/3/f/ii" IdURI="http://www.legislation.gov.uk/id/uksi/2012/2885/schedule/1/paragraph/3/f/ii" id="schedule-1-paragraph-3-f-ii"><Pnumber>ii</Pnumber><P4para><Text>amount B is 2 6/7 per cent of the difference between his income for the relevant week and his applicable amount; and</Text></P4para></P4></P3para></P3><P3 DocumentURI="http://www.legislation.gov.uk/uksi/2012/2885/schedule/1/paragraph/3/g" IdURI="http://www.legislation.gov.uk/id/uksi/2012/2885/schedule/1/paragraph/3/g" id="schedule-1-paragraph-3-g"><Pnumber>g</Pnumber><P3para><Text>who has made an application.</Text></P3para></P3></P1para></P1></P1group></Part></ScheduleBody></Schedule></Schedules></Secondary><Commentaries><Commentary Type="I" id="key-04d1d4b3e916cdc89219e22cdfbe601a"><Para><Text>Sch. 1 para. 3  in force at 27.11.2012, see <CitationSubRef id="nf967b2e049adda3c" SectionRef="regulation-1-1" URI="http://www.legislation.gov.uk/id/uksi/2012/2885/regulation/1/1" Operative="true">reg. 1(1)</CitationSubRef></Text></Para></Commentary></Commentaries></Legislation>